pyrix/__init__.py
pyrix/binarymatrix/__init__.py
pyrix/binarymatrix/binarymatrix.py
pyrix/charmatrix/__init__.py
pyrix/charmatrix/charmatrix.py
pyrix/equation/MatrixEquations.py
pyrix/equation/__init__.py
pyrix/exception/__init__.py
pyrix/exception/pyrixexceptions.py
pyrix/matrix/Matrix.py
pyrix/matrix/__init__.py
pyrix/util/__init__.py
pyrix/util/pyrixutil.py
pyrix/vector/Vector.py
pyrix/vector/__init__.py
pyrix-0.7.19.dist-info/LICENSE
pyrix-0.7.19.dist-info/METADATA
pyrix-0.7.19.dist-info/WHEEL
pyrix-0.7.19.dist-info/top_level.txt
pyrix-0.7.19.dist-info/RECORD
