Metadata-Version: 2.1
Name: pyrix
Version: 0.7.19
Summary: A matrix Library
Home-page: UNKNOWN
Author: Abhi-1U
Author-email: PerricoQ@outlook.com
License: MIT
Project-URL: Bug Tracker, https://github.com/Abhi-1U/pyrix/issues
Project-URL: Documentation, https://abhi-1u.github.io/pyrix-docs/
Project-URL: Source Code, https://github.com/Abhi-1U/pyrix
Platform: UNKNOWN
Classifier: Development Status :: 5 - Production/Stable
Classifier: Environment :: Console
Classifier: Operating System :: OS Independent
Classifier: Intended Audience :: Science/Research
Classifier: Programming Language :: Python
Classifier: Programming Language :: Python :: 3
Classifier: Programming Language :: Python :: 3.6
Classifier: Programming Language :: Python :: 3.7
Classifier: Programming Language :: Python :: 3.8
Classifier: Topic :: Scientific/Engineering
Requires-Python: >=3.0
